pyshaper/CommonObservables.py
pyshaper/GroundSpace.py
pyshaper/Manifolds.py
pyshaper/Observables.py
pyshaper/Shaper.py
pyshaper/__init__.py
pyshaper/_version.py
pyshaper/utils/__init__.py
pyshaper/utils/data_utils.py
pyshaper/utils/plot_utils.py
pyshaper-1.2.0.dist-info/METADATA
pyshaper-1.2.0.dist-info/WHEEL
pyshaper-1.2.0.dist-info/licenses/LICENSE
pyshaper-1.2.0.dist-info/RECORD
