Metadata-Version: 2.1
Name: pyshaper
Version: 1.2.0
Summary: framework for defining, building, and evaluating generalized shape observables for collider physics
Project-URL: Documentation, https://github.com/rikab/SHAPER
Project-URL: Homepage, https://github.com/rikab/SHAPER
Project-URL: Issue Tracker, https://github.com/rikab/SHAPER/issues
Project-URL: Releases, https://github.com/rikab/SHAPER/releases
Project-URL: Source Code, https://github.com/rikab/SHAPER
Author-email: Rikab Gambhir <rikab@mit.edu>
License: MIT
License-File: LICENSE
Keywords: jet physics,shape observables
Classifier: Development Status :: 3 - Alpha
Classifier: Intended Audience :: Science/Research
Classifier: License :: OSI Approved :: MIT License
Classifier: Programming Language :: Python :: 3
Classifier: Programming Language :: Python :: 3 :: Only
Classifier: Programming Language :: Python :: 3.7
Classifier: Programming Language :: Python :: 3.8
Classifier: Programming Language :: Python :: 3.9
Classifier: Programming Language :: Python :: 3.10
Classifier: Programming Language :: Python :: Implementation :: CPython
Classifier: Topic :: Scientific/Engineering
Classifier: Topic :: Scientific/Engineering :: Physics
Requires-Python: >=3.7
Requires-Dist: geomloss>=0.2.6
Requires-Dist: matplotlib>=3.5.0
Requires-Dist: numpy
Requires-Dist: pyjet>=1.9.0
Requires-Dist: scipy>=1.5.1
Requires-Dist: torch>=1.10.0
Provides-Extra: all
Requires-Dist: pyshaper[energyflow,viz]; extra == 'all'
Provides-Extra: energyflow
Requires-Dist: energyflow>=1.3.0; extra == 'energyflow'
Requires-Dist: scikit-learn>=1.2.0; extra == 'energyflow'
Requires-Dist: tensorflow-macos>=2.7.0; (platform_machine == 'arm64' and platform_system == 'Darwin') and extra == 'energyflow'
Requires-Dist: tensorflow>=2.7.0; (platform_machine != 'arm64') and extra == 'energyflow'
Provides-Extra: viz
Requires-Dist: imageio>=2.20.0; extra == 'viz'
